[{"note": "D#1", "time": 6.1000000000000005, "duration": 0.1}, {"note": "E2", "time": 6.2, "duration": 0.15000000000000002}, {"note": "E2", "time": 6.4, "duration": 0.1}, {"note": "F#2", "time": 6.7, "duration": 0.1}, {"note": "B0", "time": 6.800000000000001, "duration": 0.15000000000000002}, {"note": "D#1", "time": 6.95, "duration": 0.25}, {"note": "D#1", "time": 7.300000000000001, "duration": 0.1}, {"note": "C#2", "time": 7.4, "duration": 0.1}, {"note": "C#2", "time": 7.550000000000001, "duration": 0.30000000000000004}, {"note": "E2", "time": 8.25, "duration": 0.1}, {"note": "B1", "time": 8.35, "duration": 0.1}, {"note": "E2", "time": 8.55, "duration": 0.1}, {"note": "E2", "time": 9.05, "duration": 0.15000000000000002}, {"note": "B1", "time": 9.200000000000001, "duration": 0.1}, {"note": "B0", "time": 9.450000000000001, "duration": 0.1}, {"note": "B2", "time": 9.65, "duration": 0.15000000000000002}, {"note": "F#2", "time": 9.850000000000001, "duration": 0.2}, {"note": "F#2", "time": 10.100000000000001, "duration": 0.1}, {"note": "B2", "time": 10.200000000000001, "duration": 0.2}, {"note": "F#2", "time": 10.4, "duration": 0.1}, {"note": "B2", "time": 10.5, "duration": 0.25}, {"note": "A#2", "time": 11.100000000000001, "duration": 0.25}, {"note": "A2", "time": 11.450000000000001, "duration": 0.1}, {"note": "A#1", "time": 11.75, "duration": 0.25}, {"note": "C#2", "time": 12.0, "duration": 0.25}, {"note": "C#2", "time": 12.350000000000001, "duration": 0.5}, {"note": "C#2", "time": 13.25, "duration": 0.1}, {"note": "C#2", "time": 13.4, "duration": 0.30000000000000004}, {"note": "E2", "time": 13.75, "duration": 0.15000000000000002}, {"note": "B0", "time": 14.25, "duration": 0.15000000000000002}, {"note": "F#2", "time": 14.950000000000001, "duration": 0.1}, {"note": "B2", "time": 15.05, "duration": 0.1}, {"note": "B2", "time": 15.350000000000001, "duration": 0.15000000000000002}, {"note": "F#2", "time": 15.600000000000001, "duration": 0.25}, {"note": "E2", "time": 16.0, "duration": 0.2}, {"note": "B1", "time": 16.35, "duration": 0.1}, {"note": "C#2", "time": 16.650000000000002, "duration": 0.2}, {"note": "C#2", "time": 17.150000000000002, "duration": 0.1}, {"note": "E2", "time": 17.3, "duration": 0.1}, {"note": "A2", "time": 17.650000000000002, "duration": 0.35000000000000003}, {"note": "B1", "time": 18.05, "duration": 0.2}, {"note": "C#2", "time": 18.35, "duration": 0.2}, {"note": "E2", "time": 18.650000000000002, "duration": 0.2}, {"note": "B1", "time": 18.95, "duration": 0.15000000000000002}, {"note": "B0", "time": 19.150000000000002, "duration": 0.1}, {"note": "F#4", "time": 19.3, "duration": 0.1}, {"note": "F#2", "time": 19.6, "duration": 0.1}, {"note": "F#2", "time": 19.75, "duration": 0.15000000000000002}, {"note": "B2", "time": 19.900000000000002, "duration": 0.15000000000000002}, {"note": "F#2", "time": 20.150000000000002, "duration": 0.1}, {"note": "B0", "time": 20.3, "duration": 0.2}, {"note": "F#2", "time": 20.5, "duration": 0.25}, {"note": "A2", "time": 20.8, "duration": 0.2}, {"note": "B1", "time": 21.25, "duration": 0.1}, {"note": "A#1", "time": 21.400000000000002, "duration": 0.1}, {"note": "A#1", "time": 21.55, "duration": 0.15000000000000002}, {"note": "C#2", "time": 21.8, "duration": 0.25}, {"note": "C#2", "time": 22.1, "duration": 0.15000000000000002}, {"note": "E2", "time": 22.35, "duration": 0.15000000000000002}, {"note": "F#4", "time": 22.650000000000002, "duration": 0.1}, {"note": "B2", "time": 22.75, "duration": 0.2}, {"note": "C#2", "time": 22.950000000000003, "duration": 0.30000000000000004}, {"note": "C#2", "time": 23.3, "duration": 0.1}, {"note": "C#2", "time": 23.450000000000003, "duration": 0.1}, {"note": "E2", "time": 23.55, "duration": 0.15000000000000002}, {"note": "C#2", "time": 23.700000000000003, "duration": 0.1}, {"note": "B1", "time": 23.85, "duration": 0.1}, {"note": "F#2", "time": 23.950000000000003, "duration": 0.15000000000000002}, {"note": "B0", "time": 24.200000000000003, "duration": 0.1}, {"note": "D#2", "time": 24.35, "duration": 0.1}, {"note": "F#2", "time": 24.55, "duration": 0.2}, {"note": "F#2", "time": 24.8, "duration": 0.30000000000000004}, {"note": "D#2", "time": 25.3, "duration": 0.15000000000000002}, {"note": "F#2", "time": 25.55, "duration": 0.2}, {"note": "D#2", "time": 25.85, "duration": 0.15000000000000002}, {"note": "E3", "time": 26.35, "duration": 0.2}, {"note": "E2", "time": 26.55, "duration": 0.35000000000000003}, {"note": "B2", "time": 27.0, "duration": 0.1}, {"note": "E2", "time": 27.1, "duration": 0.30000000000000004}, {"note": "E2", "time": 27.450000000000003, "duration": 0.4}, {"note": "E2", "time": 28.1, "duration": 0.25}, {"note": "E2", "time": 28.400000000000002, "duration": 0.25}, {"note": "D#2", "time": 28.700000000000003, "duration": 0.35000000000000003}, {"note": "D#2", "time": 29.150000000000002, "duration": 0.1}, {"note": "E2", "time": 29.35, "duration": 0.15000000000000002}, {"note": "E2", "time": 29.55, "duration": 0.1}, {"note": "F#2", "time": 29.700000000000003, "duration": 0.2}, {"note": "F#2", "time": 30.05, "duration": 0.25}, {"note": "D#1", "time": 30.400000000000002, "duration": 0.1}, {"note": "E2", "time": 30.5, "duration": 0.1}, {"note": "E2", "time": 30.85, "duration": 0.1}, {"note": "B1", "time": 31.0, "duration": 0.1}, {"note": "D#2", "time": 31.150000000000002, "duration": 0.1}, {"note": "D#2", "time": 31.35, "duration": 0.4}, {"note": "E2", "time": 31.900000000000002, "duration": 0.1}, {"note": "E2", "time": 32.25, "duration": 0.1}, {"note": "E2", "time": 32.4, "duration": 0.1}, {"note": "A#1", "time": 32.75, "duration": 0.1}, {"note": "C#2", "time": 32.95, "duration": 0.35000000000000003}, {"note": "E2", "time": 33.300000000000004, "duration": 0.1}, {"note": "F#2", "time": 33.4, "duration": 0.15000000000000002}, {"note": "A2", "time": 33.550000000000004, "duration": 0.30000000000000004}, {"note": "B1", "time": 33.85, "duration": 0.1}, {"note": "F1", "time": 34.1, "duration": 0.1}, {"note": "E2", "time": 34.25, "duration": 0.2}, {"note": "E2", "time": 34.550000000000004, "duration": 0.1}, {"note": "F#2", "time": 34.9, "duration": 0.15000000000000002}, {"note": "B1", "time": 35.1, "duration": 0.2}, {"note": "D#2", "time": 35.5, "duration": 0.2}, {"note": "F#2", "time": 35.75, "duration": 0.1}, {"note": "E2", "time": 36.0, "duration": 0.15000000000000002}, {"note": "B2", "time": 36.5, "duration": 0.1}, {"note": "E2", "time": 36.65, "duration": 0.45}, {"note": "A2", "time": 37.1, "duration": 0.1}, {"note": "E2", "time": 37.2, "duration": 0.1}, {"note": "E3", "time": 37.4, "duration": 0.1}, {"note": "B1", "time": 37.5, "duration": 0.30000000000000004}, {"note": "E3", "time": 37.9, "duration": 0.1}, {"note": "E2", "time": 38.0, "duration": 0.15000000000000002}, {"note": "E2", "time": 38.2, "duration": 0.15000000000000002}, {"note": "D#2", "time": 38.400000000000006, "duration": 0.15000000000000002}, {"note": "D#2", "time": 38.6, "duration": 0.30000000000000004}, {"note": "F#2", "time": 38.95, "duration": 0.1}, {"note": "E2", "time": 39.050000000000004, "duration": 0.2}, {"note": "F#2", "time": 39.5, "duration": 0.15000000000000002}, {"note": "B0", "time": 39.85, "duration": 0.15000000000000002}, {"note": "F#2", "time": 40.1, "duration": 0.1}, {"note": "E2", "time": 40.25, "duration": 0.1}, {"note": "E2", "time": 40.400000000000006, "duration": 0.1}, {"note": "A#1", "time": 40.85, "duration": 0.2}, {"note": "C#2", "time": 41.150000000000006, "duration": 0.15000000000000002}, {"note": "C#2", "time": 41.35, "duration": 0.1}, {"note": "C#2", "time": 41.5, "duration": 0.2}, {"note": "C#2", "time": 41.75, "duration": 0.4}, {"note": "E2", "time": 42.2, "duration": 0.15000000000000002}, {"note": "C#2", "time": 42.400000000000006, "duration": 0.25}, {"note": "C#2", "time": 42.75, "duration": 0.45}, {"note": "C#2", "time": 43.25, "duration": 0.2}, {"note": "C#2", "time": 43.6, "duration": 0.45}, {"note": "E2", "time": 44.150000000000006, "duration": 0.1}, {"note": "C#2", "time": 44.35, "duration": 0.15000000000000002}, {"note": "A#1", "time": 44.5, "duration": 0.1}, {"note": "C#2", "time": 44.800000000000004, "duration": 0.15000000000000002}, {"note": "C#2", "time": 45.0, "duration": 0.1}, {"note": "B0", "time": 45.150000000000006, "duration": 0.15000000000000002}, {"note": "B0", "time": 45.35, "duration": 0.15000000000000002}, {"note": "B0", "time": 45.550000000000004, "duration": 0.1}, {"note": "F1", "time": 46.050000000000004, "duration": 0.1}, {"note": "E2", "time": 46.550000000000004, "duration": 0.1}, {"note": "E2", "time": 46.900000000000006, "duration": 0.2}, {"note": "B1", "time": 47.2, "duration": 0.2}, {"note": "E2", "time": 47.400000000000006, "duration": 0.15000000000000002}, {"note": "E2", "time": 47.6, "duration": 0.30000000000000004}, {"note": "E2", "time": 47.95, "duration": 0.1}, {"note": "B2", "time": 48.050000000000004, "duration": 0.1}, {"note": "D#2", "time": 48.2, "duration": 0.25}, {"note": "F#2", "time": 48.550000000000004, "duration": 0.2}, {"note": "E2", "time": 48.75, "duration": 0.30000000000000004}, {"note": "B0", "time": 49.25, "duration": 0.1}, {"note": "F#2", "time": 49.550000000000004, "duration": 0.25}, {"note": "B0", "time": 49.85, "duration": 0.1}, {"note": "E2", "time": 50.0, "duration": 0.15000000000000002}, {"note": "D#2", "time": 50.7, "duration": 0.30000000000000004}, {"note": "C#2", "time": 51.150000000000006, "duration": 0.2}, {"note": "E2", "time": 51.45, "duration": 0.2}, {"note": "G0", "time": 51.75, "duration": 0.25}, {"note": "C#2", "time": 52.1, "duration": 0.5}, {"note": "G0", "time": 52.6, "duration": 0.1}, {"note": "A2", "time": 53.050000000000004, "duration": 0.25}, {"note": "F1", "time": 53.400000000000006, "duration": 0.2}, {"note": "B1", "time": 53.6, "duration": 0.1}, {"note": "B1", "time": 53.75, "duration": 0.2}, {"note": "D#0", "time": 53.95, "duration": 0.30000000000000004}, {"note": "B0", "time": 54.45, "duration": 0.25}, {"note": "B0", "time": 54.75, "duration": 0.1}, {"note": "B0", "time": 54.900000000000006, "duration": 0.1}, {"note": "B0", "time": 55.050000000000004, "duration": 0.1}, {"note": "E2", "time": 55.45, "duration": 0.1}, {"note": "E2", "time": 55.6, "duration": 0.2}, {"note": "D#0", "time": 55.95, "duration": 0.1}, {"note": "B2", "time": 56.050000000000004, "duration": 0.1}, {"note": "D#0", "time": 56.2, "duration": 0.15000000000000002}, {"note": "E2", "time": 56.45, "duration": 0.15000000000000002}, {"note": "E2", "time": 56.75, "duration": 0.15000000000000002}, {"note": "B1", "time": 56.95, "duration": 0.25}, {"note": "E2", "time": 57.300000000000004, "duration": 0.1}, {"note": "E2", "time": 57.45, "duration": 0.15000000000000002}, {"note": "D#0", "time": 57.75, "duration": 0.1}, {"note": "D#2", "time": 57.85, "duration": 0.2}, {"note": "D#2", "time": 58.1, "duration": 0.25}, {"note": "E2", "time": 58.5, "duration": 0.1}, {"note": "E2", "time": 58.650000000000006, "duration": 0.1}, {"note": "F#2", "time": 59.0, "duration": 0.35000000000000003}, {"note": "F#2", "time": 59.5, "duration": 0.2}, {"note": "E2", "time": 59.800000000000004, "duration": 0.15000000000000002}, {"note": "E2", "time": 60.0, "duration": 0.1}, {"note": "E3", "time": 60.150000000000006, "duration": 0.15000000000000002}, {"note": "G0", "time": 60.400000000000006, "duration": 0.2}, {"note": "C#2", "time": 60.7, "duration": 0.1}, {"note": "G0", "time": 60.800000000000004, "duration": 0.1}, {"note": "C#2", "time": 60.95, "duration": 0.1}, {"note": "C#2", "time": 61.2, "duration": 0.1}, {"note": "G-1", "time": 61.300000000000004, "duration": 0.1}, {"note": "G0", "time": 61.5, "duration": 0.2}, {"note": "G0", "time": 61.75, "duration": 0.2}, {"note": "C#2", "time": 62.150000000000006, "duration": 0.2}, {"note": "G0", "time": 62.35, "duration": 0.1}, {"note": "G0", "time": 62.6, "duration": 0.1}, {"note": "G0", "time": 62.75, "duration": 0.30000000000000004}, {"note": "C#2", "time": 63.150000000000006, "duration": 0.1}, {"note": "C#2", "time": 63.35, "duration": 0.35000000000000003}, {"note": "G0", "time": 63.800000000000004, "duration": 0.15000000000000002}, {"note": "C#2", "time": 64.3, "duration": 0.25}, {"note": "B1", "time": 64.8, "duration": 0.1}, {"note": "F#2", "time": 64.9, "duration": 0.25}, {"note": "D#0", "time": 65.4, "duration": 0.1}, {"note": "C#2", "time": 65.55, "duration": 0.35000000000000003}, {"note": "D#0", "time": 65.9, "duration": 0.2}, {"note": "A2", "time": 66.10000000000001, "duration": 0.1}, {"note": "B0", "time": 66.4, "duration": 0.1}, {"note": "D#0", "time": 66.8, "duration": 0.1}, {"note": "C#2", "time": 67.05, "duration": 0.15000000000000002}, {"note": "C#2", "time": 67.25, "duration": 0.30000000000000004}, {"note": "G-1", "time": 67.75, "duration": 0.15000000000000002}, {"note": "B0", "time": 68.7, "duration": 0.1}, {"note": "B0", "time": 68.9, "duration": 0.15000000000000002}, {"note": "B0", "time": 69.10000000000001, "duration": 0.25}, {"note": "B2", "time": 69.60000000000001, "duration": 0.15000000000000002}, {"note": "B1", "time": 69.75, "duration": 0.15000000000000002}, {"note": "G0", "time": 70.05, "duration": 0.35000000000000003}, {"note": "G0", "time": 70.5, "duration": 0.1}, {"note": "C#2", "time": 70.60000000000001, "duration": 0.15000000000000002}, {"note": "G-1", "time": 71.0, "duration": 0.1}, {"note": "G0", "time": 71.10000000000001, "duration": 0.15000000000000002}, {"note": "A#2", "time": 71.35000000000001, "duration": 0.1}, {"note": "G0", "time": 71.5, "duration": 0.1}, {"note": "C#2", "time": 71.60000000000001, "duration": 0.1}, {"note": "G0", "time": 72.3, "duration": 0.15000000000000002}, {"note": "B1", "time": 72.5, "duration": 0.15000000000000002}, {"note": "D#2", "time": 72.9, "duration": 0.15000000000000002}, {"note": "F#2", "time": 73.05, "duration": 0.25}, {"note": "A2", "time": 73.9, "duration": 0.1}, {"note": "A#2", "time": 74.35000000000001, "duration": 0.1}, {"note": "G-1", "time": 74.75, "duration": 0.1}, {"note": "D#1", "time": 74.95, "duration": 0.2}, {"note": "D#0", "time": 75.3, "duration": 0.1}, {"note": "D#0", "time": 75.75, "duration": 0.4}, {"note": "D#0", "time": 76.2, "duration": 0.1}, {"note": "D#0", "time": 76.55, "duration": 0.1}, {"note": "C#2", "time": 76.7, "duration": 0.25}, {"note": "E2", "time": 77.05000000000001, "duration": 0.15000000000000002}, {"note": "D#2", "time": 77.60000000000001, "duration": 0.15000000000000002}, {"note": "E2", "time": 77.95, "duration": 0.2}, {"note": "F#2", "time": 78.25, "duration": 0.1}, {"note": "F#2", "time": 78.4, "duration": 0.15000000000000002}, {"note": "F#2", "time": 78.60000000000001, "duration": 0.15000000000000002}, {"note": "F#2", "time": 78.85000000000001, "duration": 0.15000000000000002}, {"note": "D#2", "time": 79.2, "duration": 0.15000000000000002}, {"note": "D#2", "time": 79.5, "duration": 0.2}, {"note": "A#1", "time": 79.7, "duration": 0.15000000000000002}, {"note": "C#2", "time": 79.85000000000001, "duration": 0.1}, {"note": "C#2", "time": 80.05000000000001, "duration": 0.2}, {"note": "G-1", "time": 80.25, "duration": 0.1}, {"note": "C#2", "time": 80.4, "duration": 0.15000000000000002}, {"note": "G0", "time": 80.60000000000001, "duration": 0.1}, {"note": "G0", "time": 80.9, "duration": 0.2}, {"note": "G0", "time": 81.15, "duration": 0.2}, {"note": "G-1", "time": 81.4, "duration": 0.1}, {"note": "C#2", "time": 81.55000000000001, "duration": 0.1}, {"note": "C#2", "time": 81.7, "duration": 0.2}, {"note": "G0", "time": 82.10000000000001, "duration": 0.1}, {"note": "B2", "time": 82.25, "duration": 0.15000000000000002}, {"note": "B2", "time": 82.45, "duration": 0.1}, {"note": "C#2", "time": 82.55000000000001, "duration": 0.1}, {"note": "C#2", "time": 82.80000000000001, "duration": 0.35000000000000003}, {"note": "B1", "time": 83.35000000000001, "duration": 0.1}, {"note": "B0", "time": 83.45, "duration": 0.15000000000000002}, {"note": "B0", "time": 83.65, "duration": 0.4}, {"note": "B0", "time": 84.10000000000001, "duration": 0.55}, {"note": "D#1", "time": 85.0, "duration": 0.1}, {"note": "C#2", "time": 85.15, "duration": 0.15000000000000002}, {"note": "D#0", "time": 85.30000000000001, "duration": 0.1}, {"note": "C#2", "time": 85.4, "duration": 0.1}, {"note": "D#0", "time": 85.7, "duration": 0.1}, {"note": "D#0", "time": 85.9, "duration": 0.1}, {"note": "D#0", "time": 86.05000000000001, "duration": 0.1}, {"note": "D#0", "time": 86.25, "duration": 0.15000000000000002}, {"note": "C#2", "time": 86.5, "duration": 0.2}, {"note": "D#0", "time": 86.7, "duration": 0.30000000000000004}, {"note": "B1", "time": 87.05000000000001, "duration": 0.15000000000000002}, {"note": "D#2", "time": 87.5, "duration": 0.1}, {"note": "B1", "time": 87.7, "duration": 0.2}, {"note": "D#0", "time": 87.9, "duration": 0.1}, {"note": "B0", "time": 88.30000000000001, "duration": 0.25}, {"note": "B0", "time": 88.60000000000001, "duration": 0.2}, {"note": "G-1", "time": 89.15, "duration": 0.30000000000000004}, {"note": "A#1", "time": 89.55000000000001, "duration": 0.15000000000000002}, {"note": "G0", "time": 89.85000000000001, "duration": 0.25}, {"note": "G-1", "time": 90.15, "duration": 0.1}, {"note": "A#2", "time": 90.75, "duration": 0.25}, {"note": "C#2", "time": 91.05000000000001, "duration": 0.1}, {"note": "G0", "time": 91.15, "duration": 0.1}, {"note": "C#2", "time": 91.45, "duration": 0.1}, {"note": "F#2", "time": 91.60000000000001, "duration": 0.15000000000000002}, {"note": "F#2", "time": 91.80000000000001, "duration": 0.1}, {"note": "B1", "time": 92.5, "duration": 0.1}, {"note": "B1", "time": 92.65, "duration": 0.1}, {"note": "B0", "time": 92.9, "duration": 0.25}, {"note": "A2", "time": 93.15, "duration": 0.2}, {"note": "B0", "time": 93.35000000000001, "duration": 0.1}, {"note": "B0", "time": 93.5, "duration": 0.25}, {"note": "A#2", "time": 93.85000000000001, "duration": 0.15000000000000002}, {"note": "G-1", "time": 94.25, "duration": 0.1}, {"note": "A2", "time": 94.4, "duration": 0.1}, {"note": "C#2", "time": 94.5, "duration": 0.2}, {"note": "C#2", "time": 94.80000000000001, "duration": 0.1}, {"note": "C#2", "time": 95.2, "duration": 0.1}, {"note": "D#0", "time": 95.30000000000001, "duration": 0.1}, {"note": "D#0", "time": 95.45, "duration": 0.15000000000000002}, {"note": "B0", "time": 95.60000000000001, "duration": 0.1}, {"note": "D#0", "time": 95.7, "duration": 0.1}, {"note": "B1", "time": 95.85000000000001, "duration": 0.1}, {"note": "D#0", "time": 95.95, "duration": 0.2}, {"note": "E2", "time": 96.25, "duration": 0.15000000000000002}, {"note": "D#2", "time": 96.80000000000001, "duration": 0.1}, {"note": "G0", "time": 96.9, "duration": 0.2}, {"note": "D#2", "time": 97.10000000000001, "duration": 0.1}, {"note": "G0", "time": 97.30000000000001, "duration": 0.1}, {"note": "G0", "time": 97.60000000000001, "duration": 1.0}, {"note": "D#2", "time": 98.65, "duration": 0.1}, {"note": "G0", "time": 98.85000000000001, "duration": 0.30000000000000004}, {"note": "D#2", "time": 99.2, "duration": 0.2}, {"note": "D#2", "time": 99.45, "duration": 0.1}, {"note": "D#2", "time": 99.60000000000001, "duration": 0.1}, {"note": "C#2", "time": 99.80000000000001, "duration": 0.15000000000000002}, {"note": "G0", "time": 100.4, "duration": 0.15000000000000002}, {"note": "G0", "time": 100.7, "duration": 0.15000000000000002}, {"note": "C#2", "time": 101.45, "duration": 0.1}, {"note": "B1", "time": 101.60000000000001, "duration": 0.1}, {"note": "B0", "time": 101.75, "duration": 0.15000000000000002}, {"note": "B0", "time": 102.0, "duration": 0.30000000000000004}, {"note": "B0", "time": 102.4, "duration": 0.45}, {"note": "B0", "time": 103.05000000000001, "duration": 0.1}, {"note": "B0", "time": 103.2, "duration": 0.25}, {"note": "G-1", "time": 103.65, "duration": 0.2}, {"note": "E3", "time": 104.15, "duration": 0.1}, {"note": "E2", "time": 104.25, "duration": 0.1}, {"note": "E2", "time": 104.4, "duration": 0.1}, {"note": "F1", "time": 104.60000000000001, "duration": 0.15000000000000002}, {"note": "D#0", "time": 105.15, "duration": 0.1}, {"note": "D#1", "time": 105.60000000000001, "duration": 0.1}, {"note": "B0", "time": 105.7, "duration": 0.1}, {"note": "D#1", "time": 105.9, "duration": 0.1}, {"note": "B0", "time": 106.0, "duration": 0.15000000000000002}, {"note": "G0", "time": 106.2, "duration": 0.2}, {"note": "G-1", "time": 106.55000000000001, "duration": 0.15000000000000002}, {"note": "E2", "time": 106.75, "duration": 0.25}, {"note": "D#0", "time": 107.05000000000001, "duration": 0.1}, {"note": "D#0", "time": 107.2, "duration": 0.2}, {"note": "E2", "time": 107.45, "duration": 0.15000000000000002}, {"note": "D#0", "time": 107.65, "duration": 0.1}, {"note": "D#0", "time": 107.95, "duration": 0.30000000000000004}, {"note": "E2", "time": 108.35000000000001, "duration": 0.15000000000000002}, {"note": "D#0", "time": 108.55000000000001, "duration": 0.1}, {"note": "D#0", "time": 108.7, "duration": 0.1}, {"note": "D#2", "time": 109.2, "duration": 0.25}, {"note": "E2", "time": 109.55000000000001, "duration": 0.25}, {"note": "F#2", "time": 110.05000000000001, "duration": 0.1}, {"note": "F#2", "time": 110.4, "duration": 0.15000000000000002}, {"note": "E2", "time": 110.80000000000001, "duration": 0.25}, {"note": "G-1", "time": 111.4, "duration": 0.15000000000000002}, {"note": "A#1", "time": 111.60000000000001, "duration": 0.15000000000000002}, {"note": "E2", "time": 112.10000000000001, "duration": 0.15000000000000002}, {"note": "G0", "time": 112.35000000000001, "duration": 0.2}, {"note": "G0", "time": 112.7, "duration": 0.15000000000000002}, {"note": "C#2", "time": 112.95, "duration": 0.1}, {"note": "G-1", "time": 113.5, "duration": 0.30000000000000004}, {"note": "G-1", "time": 113.85000000000001, "duration": 0.15000000000000002}, {"note": "E2", "time": 114.2, "duration": 0.1}, {"note": "E2", "time": 114.4, "duration": 0.15000000000000002}, {"note": "E2", "time": 114.80000000000001, "duration": 0.1}, {"note": "B0", "time": 115.10000000000001, "duration": 0.2}, {"note": "B0", "time": 115.35000000000001, "duration": 0.2}, {"note": "B0", "time": 116.05000000000001, "duration": 0.15000000000000002}, {"note": "G-1", "time": 116.25, "duration": 0.1}, {"note": "E2", "time": 116.35000000000001, "duration": 0.1}, {"note": "B1", "time": 116.5, "duration": 0.1}, {"note": "F1", "time": 116.7, "duration": 0.15000000000000002}, {"note": "E2", "time": 117.05000000000001, "duration": 0.25}, {"note": "E2", "time": 117.45, "duration": 0.25}, {"note": "B1", "time": 117.75, "duration": 0.2}, {"note": "E2", "time": 118.2, "duration": 0.15000000000000002}, {"note": "D#0", "time": 118.45, "duration": 0.1}, {"note": "G-1", "time": 118.7, "duration": 0.15000000000000002}, {"note": "D#2", "time": 119.05000000000001, "duration": 0.2}, {"note": "F#2", "time": 119.45, "duration": 0.1}, {"note": "B0", "time": 119.65, "duration": 0.2}, {"note": "B1", "time": 119.95, "duration": 0.1}, {"note": "F#2", "time": 120.25, "duration": 0.25}, {"note": "E2", "time": 120.60000000000001, "duration": 0.15000000000000002}, {"note": "E3", "time": 121.0, "duration": 0.1}, {"note": "G-1", "time": 121.10000000000001, "duration": 0.2}, {"note": "C#2", "time": 121.30000000000001, "duration": 0.1}, {"note": "G-1", "time": 121.4, "duration": 0.1}, {"note": "C#2", "time": 121.5, "duration": 0.15000000000000002}, {"note": "C#2", "time": 121.7, "duration": 0.1}, {"note": "G0", "time": 121.85000000000001, "duration": 0.4}, {"note": "E2", "time": 122.30000000000001, "duration": 0.1}, {"note": "G0", "time": 122.4, "duration": 0.1}, {"note": "C#2", "time": 122.60000000000001, "duration": 0.2}, {"note": "C#2", "time": 123.0, "duration": 0.2}, {"note": "G-1", "time": 123.25, "duration": 0.45}, {"note": "B0", "time": 123.80000000000001, "duration": 0.1}, {"note": "B0", "time": 123.95, "duration": 0.15000000000000002}, {"note": "G0", "time": 124.2, "duration": 0.2}, {"note": "E2", "time": 124.45, "duration": 0.1}, {"note": "B0", "time": 125.45, "duration": 0.15000000000000002}, {"note": "F#2", "time": 125.60000000000001, "duration": 0.1}, {"note": "G-1", "time": 126.10000000000001, "duration": 0.1}, {"note": "B1", "time": 126.2, "duration": 0.1}, {"note": "B2", "time": 126.55000000000001, "duration": 0.2}, {"note": "E2", "time": 126.85000000000001, "duration": 0.25}, {"note": "E2", "time": 127.2, "duration": 0.15000000000000002}, {"note": "B1", "time": 127.5, "duration": 0.1}, {"note": "E2", "time": 127.80000000000001, "duration": 0.30000000000000004}, {"note": "D#2", "time": 128.20000000000002, "duration": 0.15000000000000002}, {"note": "G-1", "time": 128.4, "duration": 0.1}, {"note": "D#2", "time": 128.65, "duration": 0.1}, {"note": "B0", "time": 128.9, "duration": 0.1}, {"note": "E2", "time": 129.05, "duration": 0.1}, {"note": "B0", "time": 129.20000000000002, "duration": 0.1}, {"note": "B0", "time": 129.45000000000002, "duration": 0.1}, {"note": "F#2", "time": 129.75, "duration": 0.15000000000000002}, {"note": "B0", "time": 129.9, "duration": 0.1}, {"note": "E2", "time": 130.35, "duration": 0.1}, {"note": "E2", "time": 130.5, "duration": 0.1}, {"note": "E3", "time": 130.70000000000002, "duration": 0.1}, {"note": "G-1", "time": 130.85, "duration": 0.2}, {"note": "G-1", "time": 131.35, "duration": 0.1}, {"note": "E2", "time": 131.45000000000002, "duration": 0.25}, {"note": "C#2", "time": 131.70000000000002, "duration": 0.1}, {"note": "G0", "time": 131.85, "duration": 0.15000000000000002}, {"note": "C#2", "time": 132.0, "duration": 0.15000000000000002}, {"note": "G0", "time": 132.20000000000002, "duration": 0.1}, {"note": "C#2", "time": 132.3, "duration": 0.30000000000000004}, {"note": "E2", "time": 132.70000000000002, "duration": 0.15000000000000002}, {"note": "G-1", "time": 133.0, "duration": 0.15000000000000002}, {"note": "G-1", "time": 133.3, "duration": 0.15000000000000002}, {"note": "B0", "time": 133.5, "duration": 0.15000000000000002}, {"note": "B0", "time": 133.70000000000002, "duration": 0.15000000000000002}, {"note": "F#2", "time": 133.9, "duration": 0.15000000000000002}, {"note": "B0", "time": 134.15, "duration": 0.1}, {"note": "B0", "time": 134.5, "duration": 0.30000000000000004}, {"note": "D#0", "time": 135.4, "duration": 0.15000000000000002}, {"note": "B0", "time": 135.55, "duration": 0.1}, {"note": "E2", "time": 136.0, "duration": 0.1}, {"note": "C#2", "time": 136.25, "duration": 0.1}, {"note": "D#0", "time": 136.35, "duration": 0.1}, {"note": "E2", "time": 136.9, "duration": 0.2}, {"note": "E2", "time": 137.15, "duration": 0.1}, {"note": "D#0", "time": 137.35, "duration": 0.15000000000000002}, {"note": "E2", "time": 137.5, "duration": 0.1}, {"note": "E2", "time": 137.65, "duration": 0.1}, {"note": "E2", "time": 137.8, "duration": 0.15000000000000002}, {"note": "D#2", "time": 138.15, "duration": 0.5}, {"note": "E2", "time": 138.75, "duration": 0.1}, {"note": "G0", "time": 139.05, "duration": 0.25}, {"note": "G0", "time": 139.4, "duration": 0.15000000000000002}, {"note": "G0", "time": 139.70000000000002, "duration": 0.25}, {"note": "E2", "time": 139.95000000000002, "duration": 0.15000000000000002}, {"note": "G0", "time": 140.15, "duration": 0.15000000000000002}, {"note": "G-1", "time": 140.55, "duration": 0.2}, {"note": "C#2", "time": 140.75, "duration": 0.15000000000000002}, {"note": "C#2", "time": 141.15, "duration": 0.15000000000000002}, {"note": "G-1", "time": 141.45000000000002, "duration": 0.1}, {"note": "C#2", "time": 141.75, "duration": 0.2}, {"note": "G-1", "time": 142.35, "duration": 0.1}, {"note": "G0", "time": 142.45000000000002, "duration": 0.15000000000000002}, {"note": "G-1", "time": 142.75, "duration": 0.25}, {"note": "G-1", "time": 143.15, "duration": 0.1}, {"note": "G-1", "time": 143.3, "duration": 0.1}, {"note": "C#2", "time": 143.4, "duration": 0.2}, {"note": "C#2", "time": 143.65, "duration": 0.1}, {"note": "D#2", "time": 144.3, "duration": 0.15000000000000002}, {"note": "D#2", "time": 144.5, "duration": 0.1}, {"note": "G0", "time": 144.85, "duration": 0.1}, {"note": "D#1", "time": 145.65, "duration": 0.15000000000000002}, {"note": "C#2", "time": 145.8, "duration": 0.25}, {"note": "D#1", "time": 146.1, "duration": 0.1}, {"note": "C#2", "time": 146.25, "duration": 0.1}, {"note": "D#0", "time": 146.35, "duration": 0.25}, {"note": "B0", "time": 146.65, "duration": 0.1}, {"note": "D#0", "time": 146.8, "duration": 0.1}, {"note": "D#0", "time": 147.0, "duration": 0.15000000000000002}, {"note": "C#2", "time": 147.20000000000002, "duration": 0.1}, {"note": "E2", "time": 147.55, "duration": 0.15000000000000002}, {"note": "B0", "time": 147.95000000000002, "duration": 0.5}, {"note": "B1", "time": 148.45000000000002, "duration": 0.1}, {"note": "B0", "time": 148.55, "duration": 0.2}, {"note": "B0", "time": 148.8, "duration": 0.2}, {"note": "B0", "time": 149.20000000000002, "duration": 0.15000000000000002}, {"note": "B0", "time": 149.4, "duration": 0.25}, {"note": "B1", "time": 149.65, "duration": 0.1}, {"note": "B2", "time": 149.9, "duration": 0.25}, {"note": "G-1", "time": 150.3, "duration": 0.1}, {"note": "A#1", "time": 150.65, "duration": 0.15000000000000002}, {"note": "C#2", "time": 150.85, "duration": 0.1}, {"note": "E2", "time": 151.05, "duration": 0.1}, {"note": "G-1", "time": 151.20000000000002, "duration": 0.1}, {"note": "G0", "time": 151.3, "duration": 0.15000000000000002}, {"note": "C#2", "time": 151.5, "duration": 0.2}, {"note": "C#2", "time": 151.85, "duration": 0.1}, {"note": "C#2", "time": 152.0, "duration": 0.1}, {"note": "C#2", "time": 152.20000000000002, "duration": 0.1}, {"note": "G-1", "time": 152.5, "duration": 0.1}, {"note": "G-1", "time": 152.75, "duration": 0.1}, {"note": "B0", "time": 152.85, "duration": 0.6000000000000001}, {"note": "B0", "time": 153.5, "duration": 0.4}, {"note": "D#2", "time": 153.95000000000002, "duration": 0.1}, {"note": "B0", "time": 154.20000000000002, "duration": 0.15000000000000002}, {"note": "D#1", "time": 154.55, "duration": 0.1}, {"note": "D#1", "time": 155.3, "duration": 0.1}, {"note": "C#2", "time": 155.4, "duration": 0.1}, {"note": "C#2", "time": 155.55, "duration": 0.1}, {"note": "C#2", "time": 155.70000000000002, "duration": 0.1}, {"note": "B0", "time": 155.8, "duration": 0.1}, {"note": "D#1", "time": 155.9, "duration": 0.1}, {"note": "D#0", "time": 156.25, "duration": 0.1}, {"note": "C#2", "time": 156.4, "duration": 0.15000000000000002}, {"note": "D#0", "time": 156.55, "duration": 0.15000000000000002}, {"note": "C#2", "time": 156.95000000000002, "duration": 0.1}, {"note": "C#2", "time": 157.10000000000002, "duration": 0.1}, {"note": "E2", "time": 157.20000000000002, "duration": 0.15000000000000002}, {"note": "E2", "time": 158.20000000000002, "duration": 0.2}, {"note": "B0", "time": 158.5, "duration": 0.1}, {"note": "B0", "time": 158.65, "duration": 0.1}, {"note": "B0", "time": 158.8, "duration": 0.1}, {"note": "B0", "time": 158.95000000000002, "duration": 0.25}, {"note": "B0", "time": 159.3, "duration": 0.1}, {"note": "D#2", "time": 159.5, "duration": 0.5}, {"note": "C#2", "time": 160.10000000000002, "duration": 0.15000000000000002}, {"note": "C#2", "time": 160.3, "duration": 0.1}, {"note": "C#2", "time": 160.65, "duration": 0.1}, {"note": "E2", "time": 160.75, "duration": 0.1}, {"note": "G0", "time": 161.10000000000002, "duration": 0.15000000000000002}, {"note": "C#2", "time": 161.25, "duration": 0.25}, {"note": "G-1", "time": 161.55, "duration": 0.1}, {"note": "G-1", "time": 162.15, "duration": 0.45}, {"note": "C#2", "time": 163.0, "duration": 0.4}, {"note": "B0", "time": 163.9, "duration": 0.35000000000000003}, {"note": "B1", "time": 164.25, "duration": 0.1}, {"note": "B0", "time": 164.65, "duration": 0.2}, {"note": "D#1", "time": 164.95000000000002, "duration": 0.2}, {"note": "D#0", "time": 165.3, "duration": 0.1}, {"note": "C#2", "time": 165.5, "duration": 0.30000000000000004}, {"note": "D#0", "time": 165.8, "duration": 0.1}, {"note": "D#1", "time": 166.25, "duration": 0.1}, {"note": "B1", "time": 166.4, "duration": 0.1}, {"note": "D#0", "time": 166.5, "duration": 0.15000000000000002}, {"note": "C#2", "time": 166.70000000000002, "duration": 0.15000000000000002}, {"note": "C#2", "time": 166.9, "duration": 0.25}, {"note": "C#2", "time": 167.20000000000002, "duration": 0.1}, {"note": "G-1", "time": 167.3, "duration": 0.1}, {"note": "B0", "time": 167.70000000000002, "duration": 0.15000000000000002}, {"note": "B0", "time": 167.9, "duration": 0.15000000000000002}, {"note": "B0", "time": 168.20000000000002, "duration": 0.25}, {"note": "D#2", "time": 168.55, "duration": 0.1}, {"note": "B0", "time": 168.95000000000002, "duration": 0.15000000000000002}, {"note": "F#2", "time": 169.20000000000002, "duration": 0.2}, {"note": "B2", "time": 169.4, "duration": 0.1}, {"note": "B1", "time": 169.5, "duration": 0.1}, {"note": "G-1", "time": 169.65, "duration": 0.30000000000000004}, {"note": "G-1", "time": 170.05, "duration": 0.1}, {"note": "C#2", "time": 170.35000000000002, "duration": 0.15000000000000002}, {"note": "A#1", "time": 170.75, "duration": 0.1}, {"note": "C#2", "time": 170.95000000000002, "duration": 0.4}, {"note": "C#2", "time": 171.5, "duration": 0.1}, {"note": "A2", "time": 171.60000000000002, "duration": 0.2}, {"note": "G-1", "time": 171.9, "duration": 0.1}, {"note": "G-1", "time": 172.05, "duration": 0.1}, {"note": "B0", "time": 172.4, "duration": 0.1}, {"note": "B0", "time": 172.55, "duration": 0.2}, {"note": "B0", "time": 172.8, "duration": 0.15000000000000002}, {"note": "B0", "time": 173.10000000000002, "duration": 0.15000000000000002}, {"note": "A2", "time": 173.45000000000002, "duration": 0.1}, {"note": "B0", "time": 173.65, "duration": 0.15000000000000002}, {"note": "A#2", "time": 174.05, "duration": 0.25}, {"note": "A#2", "time": 174.35000000000002, "duration": 0.15000000000000002}, {"note": "G-1", "time": 174.5, "duration": 0.1}, {"note": "D#1", "time": 174.8, "duration": 0.1}, {"note": "C#2", "time": 174.95000000000002, "duration": 0.4}, {"note": "D#0", "time": 175.5, "duration": 0.1}, {"note": "D#0", "time": 175.65, "duration": 0.15000000000000002}, {"note": "C#2", "time": 175.85000000000002, "duration": 0.2}, {"note": "D#0", "time": 176.3, "duration": 0.1}, {"note": "E2", "time": 176.45000000000002, "duration": 0.15000000000000002}, {"note": "C#2", "time": 176.70000000000002, "duration": 0.1}, {"note": "D#2", "time": 177.25, "duration": 0.25}, {"note": "E2", "time": 177.65, "duration": 0.1}, {"note": "E2", "time": 177.8, "duration": 0.1}, {"note": "G0", "time": 178.0, "duration": 0.2}, {"note": "G0", "time": 178.4, "duration": 0.15000000000000002}, {"note": "G0", "time": 178.65, "duration": 0.15000000000000002}, {"note": "E2", "time": 178.9, "duration": 0.2}, {"note": "G0", "time": 179.10000000000002, "duration": 0.25}, {"note": "G-1", "time": 179.5, "duration": 0.15000000000000002}, {"note": "C#2", "time": 179.8, "duration": 0.1}, {"note": "E2", "time": 180.10000000000002, "duration": 0.15000000000000002}, {"note": "C#2", "time": 180.35000000000002, "duration": 0.15000000000000002}, {"note": "G0", "time": 180.55, "duration": 0.1}, {"note": "G0", "time": 180.85000000000002, "duration": 0.1}, {"note": "C#2", "time": 180.95000000000002, "duration": 0.2}, {"note": "G0", "time": 181.15, "duration": 0.15000000000000002}, {"note": "C#2", "time": 181.35000000000002, "duration": 0.1}, {"note": "F#2", "time": 181.45000000000002, "duration": 0.1}, {"note": "G-1", "time": 181.70000000000002, "duration": 0.15000000000000002}, {"note": "B0", "time": 182.25, "duration": 0.1}, {"note": "F#2", "time": 182.55, "duration": 0.1}, {"note": "B0", "time": 182.65, "duration": 0.1}, {"note": "B0", "time": 182.8, "duration": 0.1}, {"note": "B0", "time": 182.95000000000002, "duration": 0.15000000000000002}, {"note": "F#2", "time": 183.15, "duration": 0.25}, {"note": "E3", "time": 183.75, "duration": 0.15000000000000002}, {"note": "F#2", "time": 183.9, "duration": 0.1}, {"note": "F#3", "time": 184.0, "duration": 0.25}, {"note": "E2", "time": 184.25, "duration": 0.15000000000000002}, {"note": "F1", "time": 184.45000000000002, "duration": 0.1}, {"note": "E2", "time": 184.65, "duration": 0.15000000000000002}, {"note": "D#0", "time": 184.85000000000002, "duration": 0.25}, {"note": "E2", "time": 185.10000000000002, "duration": 0.15000000000000002}, {"note": "E2", "time": 185.35000000000002, "duration": 0.1}, {"note": "D#0", "time": 185.55, "duration": 0.30000000000000004}, {"note": "D#0", "time": 186.05, "duration": 0.1}, {"note": "E2", "time": 186.20000000000002, "duration": 0.25}, {"note": "E3", "time": 186.55, "duration": 0.1}, {"note": "B0", "time": 186.85000000000002, "duration": 0.2}, {"note": "F#2", "time": 187.35000000000002, "duration": 0.4}, {"note": "G-1", "time": 187.8, "duration": 0.1}, {"note": "B0", "time": 188.05, "duration": 0.15000000000000002}, {"note": "B0", "time": 188.25, "duration": 0.35000000000000003}, {"note": "A3", "time": 188.65, "duration": 0.15000000000000002}, {"note": "G#3", "time": 188.95000000000002, "duration": 0.2}, {"note": "E3", "time": 189.3, "duration": 0.1}, {"note": "C#2", "time": 189.55, "duration": 0.1}, {"note": "G0", "time": 189.65, "duration": 0.1}, {"note": "G0", "time": 189.95000000000002, "duration": 0.15000000000000002}, {"note": "G0", "time": 190.3, "duration": 0.15000000000000002}, {"note": "G-1", "time": 190.45000000000002, "duration": 0.1}, {"note": "G0", "time": 190.55, "duration": 0.1}, {"note": "G0", "time": 190.70000000000002, "duration": 0.1}, {"note": "G0", "time": 191.0, "duration": 0.2}, {"note": "G0", "time": 191.3, "duration": 0.1}, {"note": "G0", "time": 191.5, "duration": 0.15000000000000002}, {"note": "C#2", "time": 191.9, "duration": 0.15000000000000002}, {"note": "G0", "time": 192.15, "duration": 0.1}, {"note": "C#2", "time": 192.25, "duration": 0.1}, {"note": "G0", "time": 192.4, "duration": 0.15000000000000002}, {"note": "G-1", "time": 192.60000000000002, "duration": 0.1}, {"note": "B1", "time": 192.8, "duration": 0.2}, {"note": "G0", "time": 193.05, "duration": 0.1}, {"note": "G0", "time": 193.3, "duration": 0.15000000000000002}, {"note": "E3", "time": 193.55, "duration": 0.15000000000000002}, {"note": "G-1", "time": 193.8, "duration": 0.15000000000000002}, {"note": "F#3", "time": 193.95000000000002, "duration": 0.1}, {"note": "B1", "time": 194.35000000000002, "duration": 0.2}, {"note": "D#0", "time": 194.55, "duration": 0.1}, {"note": "B1", "time": 194.65, "duration": 0.1}, {"note": "D#0", "time": 194.85000000000002, "duration": 0.15000000000000002}, {"note": "E2", "time": 195.10000000000002, "duration": 0.15000000000000002}, {"note": "D#0", "time": 195.25, "duration": 0.1}, {"note": "D#0", "time": 195.4, "duration": 0.1}, {"note": "B1", "time": 195.60000000000002, "duration": 0.15000000000000002}, {"note": "E2", "time": 195.9, "duration": 0.1}, {"note": "E2", "time": 196.05, "duration": 0.1}, {"note": "E3", "time": 196.20000000000002, "duration": 0.30000000000000004}, {"note": "B0", "time": 196.70000000000002, "duration": 0.1}, {"note": "B1", "time": 197.0, "duration": 0.35000000000000003}, {"note": "G-1", "time": 197.45000000000002, "duration": 0.1}, {"note": "F#2", "time": 197.55, "duration": 0.4}, {"note": "F#2", "time": 198.0, "duration": 0.1}, {"note": "B0", "time": 198.10000000000002, "duration": 0.25}, {"note": "F#2", "time": 198.8, "duration": 0.1}, {"note": "A#1", "time": 198.9, "duration": 0.2}, {"note": "A#1", "time": 199.15, "duration": 0.1}, {"note": "C#2", "time": 199.3, "duration": 0.1}, {"note": "G0", "time": 199.75, "duration": 0.15000000000000002}, {"note": "G0", "time": 199.95000000000002, "duration": 0.15000000000000002}, {"note": "G-1", "time": 200.20000000000002, "duration": 0.1}, {"note": "G0", "time": 200.70000000000002, "duration": 0.15000000000000002}, {"note": "G0", "time": 200.9, "duration": 0.2}, {"note": "G-1", "time": 201.10000000000002, "duration": 0.1}, {"note": "G0", "time": 201.20000000000002, "duration": 0.15000000000000002}, {"note": "A#1", "time": 201.45000000000002, "duration": 0.15000000000000002}, {"note": "G0", "time": 201.60000000000002, "duration": 0.1}, {"note": "C#2", "time": 201.85000000000002, "duration": 0.1}, {"note": "G0", "time": 202.20000000000002, "duration": 0.15000000000000002}, {"note": "B0", "time": 202.8, "duration": 0.2}, {"note": "B0", "time": 203.05, "duration": 0.1}, {"note": "B0", "time": 203.3, "duration": 0.2}, {"note": "B1", "time": 203.75, "duration": 0.35000000000000003}, {"note": "D#0", "time": 204.15, "duration": 0.1}, {"note": "D#0", "time": 204.5, "duration": 0.1}, {"note": "D#0", "time": 204.70000000000002, "duration": 0.25}, {"note": "D#0", "time": 205.0, "duration": 0.45}, {"note": "E2", "time": 205.45000000000002, "duration": 0.15000000000000002}, {"note": "D#0", "time": 205.60000000000002, "duration": 0.1}, {"note": "D#0", "time": 205.85000000000002, "duration": 0.15000000000000002}, {"note": "D#0", "time": 206.05, "duration": 0.15000000000000002}, {"note": "D#0", "time": 206.25, "duration": 0.30000000000000004}, {"note": "D#0", "time": 206.60000000000002, "duration": 0.1}, {"note": "D#0", "time": 206.8, "duration": 0.25}, {"note": "D#0", "time": 207.10000000000002, "duration": 0.1}, {"note": "D#0", "time": 207.25, "duration": 0.1}, {"note": "E2", "time": 207.45000000000002, "duration": 0.1}, {"note": "D#0", "time": 207.75, "duration": 0.15000000000000002}, {"note": "D#0", "time": 207.95000000000002, "duration": 0.4}, {"note": "D#0", "time": 208.5, "duration": 0.2}, {"note": "E2", "time": 208.75, "duration": 0.1}, {"note": "E2", "time": 208.9, "duration": 0.1}]